coveragecheck/__init__.py
coveragecheck/coveragecheck.py
example/__init__.py
example/lib.py
example/test.py
coveragecheck-0.0.3.dist-info/LICENSE
coveragecheck-0.0.3.dist-info/METADATA
coveragecheck-0.0.3.dist-info/WHEEL
coveragecheck-0.0.3.dist-info/entry_points.txt
coveragecheck-0.0.3.dist-info/top_level.txt
coveragecheck-0.0.3.dist-info/RECORD
