Metadata-Version: 2.1
Name: coveragecheck
Version: 0.0.3
Summary: Set of tools for validating code coverage as a merge criterion in a CI pipeline.
Home-page: https://github.com/jdn5126/CoverageChecker
Author: Jeff Nelson, Dave Campbell, and Colton Saska
Author-email: colt.saska@gmail.com
License: UNKNOWN
Platform: UNKNOWN
Classifier: Programming Language :: Python :: 3
Classifier: License :: OSI Approved :: MIT License
Classifier: Operating System :: OS Independent
Requires-Python: >=3.6
Requires-Dist: coverage
